gitsnippet/__init__.py
gitsnippet/plugin.py
mkdocs_gitsnippet_plugin-1.2.0.dist-info/LICENSE
mkdocs_gitsnippet_plugin-1.2.0.dist-info/METADATA
mkdocs_gitsnippet_plugin-1.2.0.dist-info/WHEEL
mkdocs_gitsnippet_plugin-1.2.0.dist-info/entry_points.txt
mkdocs_gitsnippet_plugin-1.2.0.dist-info/top_level.txt
mkdocs_gitsnippet_plugin-1.2.0.dist-info/RECORD
