Metadata-Version: 2.1
Name: mkdocs-gitsnippet-plugin
Version: 1.2.0
Summary: Mkdocs plugin that allow to inject snippet or all markdown content from a given remote git repository.
Home-page: https://github.com/SamazoOo/mkdocs-gitsnippet-plugin
Author: Samuel Comino
Author-email: samuel.covi@gmail.com
License: MIT
Keywords: mkdocs python markdown snippet git
Platform: UNKNOWN
Classifier: Development Status :: 5 - Production/Stable
Classifier: Intended Audience :: Developers
Classifier: Intended Audience :: Information Technology
Classifier: License :: OSI Approved :: MIT License
Classifier: Programming Language :: Python
Classifier: Programming Language :: Python :: 2
Classifier: Programming Language :: Python :: 2.7
Classifier: Programming Language :: Python :: 3
Classifier: Programming Language :: Python :: 3.4
Classifier: Programming Language :: Python :: 3.5
Classifier: Programming Language :: Python :: 3.6
Classifier: Programming Language :: Python :: 3.7
Requires-Python: >=2.7.9,!=3.0.*,!=3.1.*,!=3.2.*,!=3.3.*
Requires-Dist: mkdocs (>=0.17)
Requires-Dist: gitpython
